SharkReportPlugin/__init__.py
SharkReportPlugin/sharkReport.py
SharkReportPlugin/reports/sharkreport.html
pytest_sharkreport-1.0.1.dist-info/METADATA
pytest_sharkreport-1.0.1.dist-info/WHEEL
pytest_sharkreport-1.0.1.dist-info/entry_points.txt
pytest_sharkreport-1.0.1.dist-info/top_level.txt
pytest_sharkreport-1.0.1.dist-info/RECORD
